{
  "cli": {
    "version": ">= 3.7.2"
  },
  "build": {
    "development": {
      "node": "16.13.0",
      "developmentClient": true,
      "distribution": "internal",
      "ios": {
        "resourceClass": "m1-medium"
      }
    },
    "preview": {
      "distribution": "internal",
      "ios": {
        "resourceClass": "m1-medium",
        "image": "macos-monterey-12.4-xcode-13.4"
      }
    },
    "production": {
      "ios": {
        "resourceClass": "m1-medium"
      }
    }
  },
  "submit": {
    "production": {}
  }
}
